{"version": 0.6, "generator": "Overpass API 0.7.62.8 e802775f", "osm3s": {"timestamp_osm_base": "2025-11-08T10:09:35Z", "copyright": "The data included in this document is from www.openstreetmap.org. The data is made available under ODbL."}, "elements": [{"type": "node", "id": 1235035743, "lat": 52.6671904, "lon": -8.6138853}, {"type": "node", "id": 1235035762, "lat": 52.6665649, "lon": -8.6132736}, {"type": "node", "id": 1235035792, "lat": 52.6666885, "lon": -8.6141049}, {"type": "node", "id": 1235035806, "lat": 52.6663955, "lon": -8.6141501}, {"type": "node", "id": 1235035819, "lat": 52.6672051, "lon": -8.6136336}, {"type": "node", "id": 1235035825, "lat": 52.6664396, "lon": -8.614192}, {"type": "node", "id": 1235035835, "lat": 52.6663277, "lon": -8.6138419}, {"type": "node", "id": 1235035849, "lat": 52.6670749, "lon": -8.6135448}, {"type": "node", "id": 1235035853, "lat": 52.6661905, "lon": -8.6129302}, {"type": "node", "id": 1235035881, "lat": 52.6672383, "lon": -8.6137401}, {"type": "node", "id": 1235035886, "lat": 52.6663632, "lon": -8.6140645}, {"type": "node", "id": 1235035893, "lat": 52.6656854, "lon": -8.613107}, {"type": "node", "id": 1235035913, "lat": 52.6672276, "lon": -8.61369}, {"type": "node", "id": 1235035944, "lat": 52.665993, "lon": -8.6130019}, {"type": "node", "id": 1235035950, "lat": 52.6672158, "lon": -8.613845}, {"type": "node", "id": 1235035973, "lat": 52.6672334, "lon": -8.6137885}, {"type": "node", "id": 1235035981, "lat": 52.665819, "lon": -8.6130638, "tags": {"barrier": "gate"}}, {"type": "node", "id": 1235036000, "lat": 52.6664856, "lon": -8.6141936}, {"type": "node", "id": 4520748947, "lat": 52.6668327, "lon": -8.6139107, "tags": {"natural": "tree"}}, {"type": "node", "id": 4520748948, "lat": 52.6669979, "lon": -8.6138677, "tags": {"natural": "tree"}}, {"type": "node", "id": 4520748949, "lat": 52.6668345, "lon": -8.6137444, "tags": {"natural": "tree"}}, {"type": "node", "id": 4520751093, "lat": 52.666796, "lon": -8.6141547, "tags": {"natural": "tree"}}, {"type": "node", "id": 4520751094, "lat": 52.66701, "lon": -8.614059, "tags": {"natural": "tree"}}, {"type": "way", "id": 151580805, "nodes": [1235035893, 1235035981, 1235035944, 1235035853, 1235035835, 1235035886, 1235035806, 1235035825, 1235036000, 1235035792, 1235035743, 1235035950, 1235035973, 1235035881, 1235035913, 1235035819, 1235035849, 1235035762, 1235035792], "tags": {"highway": "footway", "lit": "no"}}]}