{"version": 0.6, "generator": "Overpass API 0.7.62.8 e802775f", "osm3s": {"timestamp_osm_base": "2025-11-08T12:33:51Z", "copyright": "The data included in this document is from www.openstreetmap.org. The data is made available under ODbL."}, "elements": [{"type": "node", "id": 135993252, "lat": 52.5204275, "lon": -7.8870989}, {"type": "node", "id": 271230804, "lat": 52.5142085, "lon": -7.8906939}, {"type": "node", "id": 271230805, "lat": 52.5145053, "lon": -7.8907639}, {"type": "node", "id": 271230806, "lat": 52.514723, "lon": -7.8908377}, {"type": "node", "id": 276050731, "lat": 52.5178547, "lon": -7.880855, "tags": {"crossing": "uncontrolled", "crossing_ref": "zebra", "highway": "crossing"}}, {"type": "node", "id": 276050732, "lat": 52.517461, "lon": -7.8814808}, {"type": "node", "id": 276050733, "lat": 52.5167836, "lon": -7.8825211}, {"type": "node", "id": 276050734, "lat": 52.5164252, "lon": -7.8830999}, {"type": "node", "id": 276050735, "lat": 52.5161775, "lon": -7.8835754}, {"type": "node", "id": 276050767, "lat": 52.5159467, "lon": -7.88413}, {"type": "node", "id": 276050768, "lat": 52.5158152, "lon": -7.8844493}, {"type": "node", "id": 276050769, "lat": 52.5157524, "lon": -7.8845916}, {"type": "node", "id": 1390127373, "lat": 52.5143609, "lon": -7.8907208}, {"type": "node", "id": 1614353534, "lat": 52.5158818, "lon": -7.8908772}, {"type": "node", "id": 1614353749, "lat": 52.5199056, "lon": -7.886675}, {"type": "node", "id": 1614353751, "lat": 52.5200582, "lon": -7.88663, "tags": {"direction": "backward", "highway": "give_way"}}, {"type": "node", "id": 1614353766, "lat": 52.5200315, "lon": -7.8868297, "tags": {"direction": "forward", "highway": "give_way"}}, {"type": "node", "id": 1614353791, "lat": 52.5201643, "lon": -7.8866484}, {"type": "node", "id": 1614353794, "lat": 52.5201763, "lon": -7.8865437}, {"type": "node", "id": 1614353797, "lat": 52.5202043, "lon": -7.8864482}, {"type": "node", "id": 1614353805, "lat": 52.5202485, "lon": -7.8869459}, {"type": "node", "id": 1614353807, "lat": 52.5203766, "lon": -7.8862712}, {"type": "node", "id": 1614353810, "lat": 52.5203987, "lon": -7.886244}, {"type": "node", "id": 1614353815, "lat": 52.5205511, "lon": -7.8872706}, {"type": "node", "id": 1614353830, "lat": 52.5208663, "lon": -7.8876997}, {"type": "node", "id": 1634339471, "lat": 52.5165065, "lon": -7.882958}, {"type": "node", "id": 1634339524, "lat": 52.5187689, "lon": -7.8853924}, {"type": "node", "id": 1897048359, "lat": 52.5162709, "lon": -7.8833683}, {"type": "node", "id": 1897048376, "lat": 52.5171272, "lon": -7.8820025}, {"type": "node", "id": 1897048495, "lat": 52.5179023, "lon": -7.8807623}, {"type": "node", "id": 2870196123, "lat": 52.5171113, "lon": -7.8852575}, {"type": "node", "id": 2870196129, "lat": 52.5170272, "lon": -7.8853754}, {"type": "node", "id": 2870196132, "lat": 52.5174368, "lon": -7.8843454}, {"type": "node", "id": 2870196133, "lat": 52.5175902, "lon": -7.8856892}, {"type": "node", "id": 2870196138, "lat": 52.5188674, "lon": -7.8869005}, {"type": "node", "id": 2870196145, "lat": 52.5171613, "lon": -7.8851875}, {"type": "node", "id": 2870196147, "lat": 52.5172608, "lon": -7.8847074}, {"type": "node", "id": 2870196149, "lat": 52.5173291, "lon": -7.8854961}, {"type": "node", "id": 2870196151, "lat": 52.5174613, "lon": -7.8856168}, {"type": "node", "id": 3766589722, "lat": 52.5142511, "lon": -7.8888487}, {"type": "node", "id": 3766589725, "lat": 52.5145251, "lon": -7.8880678}, {"type": "node", "id": 3766589726, "lat": 52.5145765, "lon": -7.8891495}, {"type": "node", "id": 3766589730, "lat": 52.5148674, "lon": -7.8855783}, {"type": "node", "id": 3766589731, "lat": 52.5149603, "lon": -7.8909564}, {"type": "node", "id": 3766589734, "lat": 52.5152069, "lon": -7.8901519}, {"type": "node", "id": 3766589735, "lat": 52.5153198, "lon": -7.884381}, {"type": "node", "id": 3766589737, "lat": 52.5154164, "lon": -7.8862299}, {"type": "node", "id": 3766589742, "lat": 52.5156859, "lon": -7.8848933}, {"type": "node", "id": 3766589745, "lat": 52.5157942, "lon": -7.8846456}, {"type": "node", "id": 3766589746, "lat": 52.5159205, "lon": -7.8905934}, {"type": "node", "id": 3766589753, "lat": 52.5166847, "lon": -7.8909438}, {"type": "node", "id": 3766589754, "lat": 52.5167318, "lon": -7.8855691}, {"type": "node", "id": 3766589757, "lat": 52.5169564, "lon": -7.8851301}, {"type": "node", "id": 3766589758, "lat": 52.5172712, "lon": -7.8909722}, {"type": "node", "id": 3766589760, "lat": 52.5174411, "lon": -7.8841829}, {"type": "node", "id": 3766589761, "lat": 52.5176951, "lon": -7.8858178}, {"type": "node", "id": 3766589762, "lat": 52.5177011, "lon": -7.88753}, {"type": "node", "id": 3766589763, "lat": 52.517808, "lon": -7.8882207}, {"type": "node", "id": 3766589764, "lat": 52.517857, "lon": -7.8885324}, {"type": "node", "id": 3766589766, "lat": 52.5179105, "lon": -7.8832661}, {"type": "node", "id": 3766589768, "lat": 52.5180354, "lon": -7.8852541}, {"type": "node", "id": 3766589770, "lat": 52.5180756, "lon": -7.886138}, {"type": "node", "id": 3766589771, "lat": 52.5180856, "lon": -7.8803955}, {"type": "node", "id": 3766589773, "lat": 52.5181792, "lon": -7.885128}, {"type": "node", "id": 3766589774, "lat": 52.5181855, "lon": -7.8894947}, {"type": "node", "id": 3766589775, "lat": 52.5182365, "lon": -7.8868617}, {"type": "node", "id": 3766589776, "lat": 52.5182798, "lon": -7.8850257}, {"type": "node", "id": 3766589778, "lat": 52.5183562, "lon": -7.8841554}, {"type": "node", "id": 3766589779, "lat": 52.5184274, "lon": -7.8843782}, {"type": "node", "id": 3766589780, "lat": 52.518524, "lon": -7.8839382}, {"type": "node", "id": 3766589781, "lat": 52.5185275, "lon": -7.8856597}, {"type": "node", "id": 3766589783, "lat": 52.5185576, "lon": -7.8806081}, {"type": "node", "id": 3766589784, "lat": 52.5186239, "lon": -7.884122}, {"type": "node", "id": 3766589792, "lat": 52.5188861, "lon": -7.8852619}, {"type": "node", "id": 3766589794, "lat": 52.5189195, "lon": -7.8865367}, {"type": "node", "id": 3766589797, "lat": 52.5190841, "lon": -7.885655}, {"type": "node", "id": 3766589798, "lat": 52.5193093, "lon": -7.8855447}, {"type": "node", "id": 3766589801, "lat": 52.5198765, "lon": -7.8876958}, {"type": "node", "id": 3766589802, "lat": 52.5199036, "lon": -7.885844}, {"type": "node", "id": 3766589803, "lat": 52.5199436, "lon": -7.8870495}, {"type": "node", "id": 3766589804, "lat": 52.5204322, "lon": -7.8877627}, {"type": "node", "id": 3766589805, "lat": 52.5204696, "lon": -7.8861105}, {"type": "node", "id": 3766589807, "lat": 52.5208674, "lon": -7.8881673}, {"type": "node", "id": 3766589808, "lat": 52.5210196, "lon": -7.8878793}, {"type": "node", "id": 3844627565, "lat": 52.5171394, "lon": -7.8847547}, {"type": "node", "id": 3844627566, "lat": 52.5171905, "lon": -7.8848224}, {"type": "node", "id": 3844627567, "lat": 52.5171647, "lon": -7.8848749}, {"type": "node", "id": 3844627568, "lat": 52.5171796, "lon": -7.8848947}, {"type": "node", "id": 3844627569, "lat": 52.5171355, "lon": -7.8849846}, {"type": "node", "id": 3844627570, "lat": 52.5171472, "lon": -7.885}, {"type": "node", "id": 3844627571, "lat": 52.5170544, "lon": -7.8852508}, {"type": "node", "id": 3844627572, "lat": 52.5169584, "lon": -7.8851237}, {"type": "node", "id": 3844627573, "lat": 52.5167968, "lon": -7.8857761}, {"type": "node", "id": 3844627574, "lat": 52.5168547, "lon": -7.8856557}, {"type": "node", "id": 5624025942, "lat": 52.5142887, "lon": -7.8907081}, {"type": "node", "id": 5842626200, "lat": 52.5179963, "lon": -7.8851856}, {"type": "node", "id": 5842626201, "lat": 52.5180448, "lon": -7.8852479}, {"type": "node", "id": 6360214624, "lat": 52.5157712, "lon": -7.8845465, "tags": {"direction": "forward", "highway": "stop"}}, {"type": "node", "id": 8343288654, "lat": 52.514946, "lon": -7.8909493}, {"type": "node", "id": 8343497404, "lat": 52.5171644, "lon": -7.8854096}, {"type": "node", "id": 8343497405, "lat": 52.5170398, "lon": -7.8856726}, {"type": "node", "id": 8343497406, "lat": 52.5171262, "lon": -7.8857831}, {"type": "node", "id": 8343497407, "lat": 52.5172508, "lon": -7.8855202}, {"type": "node", "id": 8343520545, "lat": 52.5169104, "lon": -7.8856402}, {"type": "node", "id": 8343520546, "lat": 52.5169344, "lon": -7.8856706}, {"type": "node", "id": 8343520547, "lat": 52.5170352, "lon": -7.8857966}, {"type": "node", "id": 8343520548, "lat": 52.5169791, "lon": -7.8857255}, {"type": "node", "id": 8343520549, "lat": 52.5169468, "lon": -7.8855627}, {"type": "node", "id": 8343520550, "lat": 52.517071, "lon": -7.8857203}, {"type": "node", "id": 8343520551, "lat": 52.5168942, "lon": -7.8857561}, {"type": "node", "id": 8343520552, "lat": 52.5169384, "lon": -7.8858122}, {"type": "node", "id": 8343520553, "lat": 52.5168276, "lon": -7.8856209}, {"type": "node", "id": 8343520554, "lat": 52.5167616, "lon": -7.8857561}, {"type": "node", "id": 8343520555, "lat": 52.516548, "lon": -7.8854674}, {"type": "node", "id": 8343520556, "lat": 52.5166288, "lon": -7.8853059}, {"type": "node", "id": 8343520557, "lat": 52.5167701, "lon": -7.8857418}, {"type": "node", "id": 8343520559, "lat": 52.5168838, "lon": -7.8856931}, {"type": "node", "id": 8343520560, "lat": 52.5168263, "lon": -7.8858141}, {"type": "node", "id": 8343520561, "lat": 52.5168311, "lon": -7.8858452}, {"type": "node", "id": 8343520562, "lat": 52.5168809, "lon": -7.8857393}, {"type": "node", "id": 8343520563, "lat": 52.5170084, "lon": -7.885901}, {"type": "node", "id": 8343520564, "lat": 52.5169586, "lon": -7.886007}, {"type": "node", "id": 8350514441, "lat": 52.5200031, "lon": -7.8866268}, {"type": "node", "id": 8350514442, "lat": 52.5199862, "lon": -7.8867921}, {"type": "node", "id": 8354041325, "lat": 52.5169594, "lon": -7.8851689}, {"type": "node", "id": 8354041326, "lat": 52.5170152, "lon": -7.8852428}, {"type": "node", "id": 8354041327, "lat": 52.5170283, "lon": -7.8852162}, {"type": "node", "id": 8354041328, "lat": 52.5169725, "lon": -7.8851423}, {"type": "node", "id": 8354041329, "lat": 52.5171511, "lon": -7.8850537}, {"type": "node", "id": 8354041330, "lat": 52.5171328, "lon": -7.8850294}, {"type": "node", "id": 8354041348, "lat": 52.5168422, "lon": -7.8855917}, {"type": "node", "id": 11330150118, "lat": 52.520795, "lon": -7.8876076}, {"type": "node", "id": 11330150121, "lat": 52.5205703, "lon": -7.8873022}, {"type": "node", "id": 11506895349, "lat": 52.5159014, "lon": -7.8907334}, {"type": "node", "id": 11506895355, "lat": 52.5158902, "lon": -7.8908156}, {"type": "node", "id": 11928314793, "lat": 52.5206956, "lon": -7.8874792}, {"type": "node", "id": 12878616360, "lat": 52.5186975, "lon": -7.8854715}, {"type": "way", "id": 148327035, "nodes": [8350514442, 1614353749, 8350514441]}, {"type": "way", "id": 179354093, "nodes": [1897048495, 276050731, 276050732, 1897048376, 276050733, 1634339471], "tags": {"highway": "secondary", "lanes": "2", "lit": "yes", "maxspeed": "50", "ref": "R691"}}, {"type": "way", "id": 283107923, "nodes": [2870196132, 2870196147, 2870196145, 2870196123, 2870196129, 3844627574], "tags": {"highway": "residential", "name": "Roselawn Close"}}, {"type": "way", "id": 283107929, "nodes": [2870196123, 2870196149, 2870196151, 2870196133], "tags": {"highway": "residential"}}, {"type": "way", "id": 292189591, "nodes": [1634339471, 276050734, 1897048359, 276050735, 276050767, 276050768], "tags": {"highway": "secondary", "lanes": "2", "lit": "yes", "maxspeed": "50", "name": "Abbeyside", "ref": "R691", "surface": "asphalt"}}, {"type": "way", "id": 292189594, "nodes": [276050769, 3766589745], "tags": {"highway": "secondary", "lanes": "2", "lit": "yes", "maxspeed": "50", "name": "Lower Friar Street", "ref": "R692", "surface": "asphalt"}}, {"type": "way", "id": 372409187, "nodes": [1614353751, 1614353791], "tags": {"highway": "secondary", "lanes": "2", "maxspeed": "50", "name": "Ladyswell Street", "ref": "R639", "surface": "asphalt"}}, {"type": "way", "id": 373145997, "nodes": [3766589775, 2870196138]}, {"type": "way", "id": 373146013, "nodes": [3766589758, 3766589774]}, {"type": "way", "id": 373146022, "nodes": [3766589746, 3766589753, 3766589758]}, {"type": "way", "id": 373146030, "nodes": [271230804, 3766589726, 3766589722]}, {"type": "way", "id": 373146032, "nodes": [276050768, 3766589754, 3766589757]}, {"type": "way", "id": 373146034, "nodes": [3766589763, 3766589762, 3766589775]}, {"type": "way", "id": 373146035, "nodes": [1614353534, 3766589734, 3766589731]}, {"type": "way", "id": 373146040, "nodes": [3766589774, 3766589764, 3766589763]}, {"type": "way", "id": 373146042, "nodes": [3766589801, 3766589803, 3766589794]}, {"type": "way", "id": 373146046, "nodes": [3766589801, 3766589804, 3766589807, 3766589808]}, {"type": "way", "id": 373146048, "nodes": [3766589775, 3766589770, 3766589761, 3766589757]}, {"type": "way", "id": 373146059, "nodes": [3766589792, 3766589797, 3766589798, 3766589802, 3766589805]}, {"type": "way", "id": 373146063, "nodes": [3766589757, 3766589760, 5842626200, 3766589768, 5842626201, 3766589773, 3766589776, 3766589781]}, {"type": "way", "id": 373146076, "nodes": [3766589722, 3766589725, 3766589737, 3766589730, 3766589735, 3766589742, 3766589745]}, {"type": "way", "id": 373146091, "nodes": [1897048495, 3766589771, 3766589783, 3766589766, 3766589778, 3766589780, 3766589784, 3766589779, 3766589792]}, {"type": "way", "id": 373146094, "nodes": [276050768, 6360214624, 276050769], "tags": {"highway": "secondary", "lanes": "2", "lit": "yes", "maxspeed": "50", "name": "Abbeyside", "ref": "R691", "surface": "asphalt"}}, {"type": "way", "id": 373146095, "nodes": [3766589805, 1614353810, 1614353807, 1614353797, 1614353794, 1614353791], "tags": {"highway": "residential", "name": "Bohereenglass", "surface": "asphalt"}}, {"type": "way", "id": 373146096, "nodes": [3766589781, 12878616360, 1634339524, 3766589792], "tags": {"highway": "tertiary", "lanes": "2", "name": "Bohermore", "surface": "asphalt"}}, {"type": "way", "id": 373146121, "nodes": [1614353534, 11506895355, 11506895349, 3766589746], "tags": {"cycleway:both": "no", "highway": "secondary", "lane_markings": "yes", "lanes": "2", "lit": "yes", "logainm:ref": "1429233", "logainm:url": "https://www.logainm.ie/1429233.aspx", "maxspeed": "50", "name": "Main Street", "name:en": "Main Street", "ref": "R639", "sidewalk": "both", "surface": "asphalt"}}, {"type": "way", "id": 373146141, "nodes": [271230804, 5624025942, 1390127373, 271230805, 271230806, 8343288654, 3766589731], "tags": {"covered": "no", "cycleway:both": "no", "highway": "secondary", "lane_markings": "yes", "lanes": "2", "lit": "yes", "maxspeed": "50", "ref": "R639", "sidewalk": "both", "surface": "asphalt"}}, {"type": "way", "id": 373146143, "nodes": [3766589808, 1614353830, 11330150118, 11928314793, 11330150121, 1614353815, 135993252, 1614353805, 1614353766], "tags": {"cycleway:both": "no", "highway": "secondary", "lanes": "2", "lit": "yes", "maxspeed": "50", "ref": "R660", "sidewalk:left": "no", "sidewalk:right": "separate", "smoothness": "good", "surface": "asphalt"}}, {"type": "way", "id": 373146172, "nodes": [3766589794, 2870196138], "tags": {"highway": "residential", "lanes": "1", "maxspeed": "50", "name": "Collier's Lane", "oneway": "yes"}}, {"type": "way", "id": 381225750, "nodes": [3844627565, 3844627566, 3844627567, 3844627568, 3844627569, 3844627570, 8354041330, 8354041329, 3844627571, 8354041327, 8354041326, 8354041325, 8354041328, 3844627572, 3844627565], "tags": {"amenity": "library", "building": "yes"}}, {"type": "way", "id": 897741814, "nodes": [8343497407, 8343497404, 8343497405, 8343497406, 8343497407], "tags": {"building": "yes"}}, {"type": "way", "id": 897742614, "nodes": [8343520553, 8354041348, 8343520556, 8343520555, 8343520554, 8343520557, 8343520553], "tags": {"building": "office"}}, {"type": "way", "id": 897742615, "nodes": [8343520560, 8343520559, 3844627574, 8343520553, 8343520557, 3844627573, 8343520560], "tags": {"building": "yes"}}, {"type": "way", "id": 897742616, "nodes": [8343520564, 8343520563, 8343520552, 8343520548, 8343520547, 8343520550, 8343520549, 8343520545, 8343520546, 8343520551, 8343520562, 8343520561, 8343520564], "tags": {"building": "yes"}}, {"type": "way", "id": 898629160, "nodes": [8350514441, 1614353751], "tags": {"highway": "secondary", "lanes": "2", "maxspeed": "50", "name": "Ladyswell Street", "ref": "R639", "smoothness": "excellent", "surface": "asphalt"}}, {"type": "way", "id": 898629161, "nodes": [1614353766, 8350514442], "tags": {"cycleway:both": "no", "highway": "secondary", "lanes": "2", "lit": "yes", "maxspeed": "50", "ref": "R660", "sidewalk:left": "no", "sidewalk:right": "separate", "smoothness": "excellent", "surface": "asphalt"}}, {"type": "relation", "id": 5550043, "members": [{"type": "way", "ref": 373146034, "role": "outer"}, {"type": "way", "ref": 373146040, "role": "outer"}, {"type": "way", "ref": 373146013, "role": "outer"}, {"type": "way", "ref": 373146022, "role": "outer"}, {"type": "way", "ref": 373146121, "role": "outer"}, {"type": "way", "ref": 373146035, "role": "outer"}, {"type": "way", "ref": 373146141, "role": "outer"}, {"type": "way", "ref": 373146030, "role": "outer"}, {"type": "way", "ref": 373146076, "role": "outer"}, {"type": "way", "ref": 292189594, "role": "outer"}, {"type": "way", "ref": 373146094, "role": "outer"}, {"type": "way", "ref": 373146032, "role": "outer"}, {"type": "way", "ref": 373146048, "role": "outer"}], "tags": {"admin_level": "10", "boundary": "administrative", "locality": "townland", "logainm:ref": "47909", "logainm:url": "https://www.logainm.ie/47909.aspx", "name": "Cashel", "name:en": "Cashel", "name:ga": "Caiseal", "place": "locality", "type": "boundary", "wikidata": "Q104316481"}}, {"type": "relation", "id": 5550063, "members": [{"type": "way", "ref": 373146048, "role": "outer"}, {"type": "way", "ref": 373146063, "role": "outer"}, {"type": "way", "ref": 373146096, "role": "outer"}, {"type": "way", "ref": 373146059, "role": "outer"}, {"type": "way", "ref": 373146095, "role": "outer"}, {"type": "way", "ref": 372409187, "role": "outer"}, {"type": "way", "ref": 898629160, "role": "outer"}, {"type": "way", "ref": 148327035, "role": "outer"}, {"type": "way", "ref": 898629161, "role": "outer"}, {"type": "way", "ref": 373146143, "role": "outer"}, {"type": "way", "ref": 373146046, "role": "outer"}, {"type": "way", "ref": 373146042, "role": "outer"}, {"type": "way", "ref": 373146172, "role": "outer"}, {"type": "way", "ref": 373145997, "role": "outer"}], "tags": {"admin_level": "10", "boundary": "administrative", "locality": "townland", "logainm:ref": "47911", "logainm:url": "https://www.logainm.ie/47911.aspx", "name": "Lady's Well", "name:en": "Lady's Well", "name:ga": "Tobar Mhuire", "place": "locality", "type": "boundary", "wikidata": "Q104316488"}}, {"type": "relation", "id": 5550078, "members": [{"type": "way", "ref": 373146091, "role": "outer"}, {"type": "way", "ref": 373146096, "role": "outer"}, {"type": "way", "ref": 373146063, "role": "outer"}, {"type": "way", "ref": 373146032, "role": "outer"}, {"type": "way", "ref": 292189591, "role": "outer"}, {"type": "way", "ref": 179354093, "role": "outer"}], "tags": {"admin_level": "10", "alt_name:en": "St. Francisabbey", "boundary": "administrative", "locality": "townland", "logainm:ref": "47912", "logainm:url": "https://www.logainm.ie/47912.aspx", "name": "Saint Francisabbey", "name:en": "Saint Francisabbey", "name:ga": "Mainistir Phroinsias", "place": "locality", "type": "boundary", "wikidata": "Q104316389"}}]}